django_hookflow/__init__.py
django_hookflow/admin.py
django_hookflow/apps.py
django_hookflow/dlq.py
django_hookflow/exceptions.py
django_hookflow/models.py
django_hookflow/persistence.py
django_hookflow/retry.py
django_hookflow/urls.py
django_hookflow/management/__init__.py
django_hookflow/management/commands/__init__.py
django_hookflow/management/commands/cleanup_workflows.py
django_hookflow/migrations/0001_initial.py
django_hookflow/migrations/__init__.py
django_hookflow/qstash/__init__.py
django_hookflow/qstash/client.py
django_hookflow/qstash/receiver.py
django_hookflow/workflows/__init__.py
django_hookflow/workflows/context.py
django_hookflow/workflows/decorator.py
django_hookflow/workflows/handlers.py
django_hookflow/workflows/registry.py
django_hookflow/workflows/urls.py
django_hookflow/workflows/views.py
django_hookflow-0.0.4.dist-info/METADATA
django_hookflow-0.0.4.dist-info/WHEEL
django_hookflow-0.0.4.dist-info/top_level.txt
django_hookflow-0.0.4.dist-info/RECORD
