Metadata-Version: 2.4
Name: django-hookflow
Version: 0.0.4
Summary: Durable workflows for Django.
Author-email: Justin Mitchel <justin@codingforentrepreneurs.com>
Project-URL: Changelog, https://github.com/jmitchel3/django-hookflow
Project-URL: Documentation, https://github.com/jmitchel3/django-hookflow
Project-URL: Funding, https://github.com/jmitchel3/django-hookflow
Project-URL: Repository, https://github.com/jmitchel3/django-hookflow
Classifier: Development Status :: 4 - Beta
Classifier: Framework :: Django :: 4.2
Classifier: Framework :: Django :: 5.0
Classifier: Framework :: Django :: 5.1
Classifier: Framework :: Django :: 5.2
Classifier: Framework :: Django :: 6.0
Classifier: Intended Audience :: Developers
Classifier: License :: OSI Approved :: MIT License
Classifier: Natural Language :: English
Classifier: Operating System :: OS Independent
Classifier: Programming Language :: Python :: 3 :: Only
Classifier: Programming Language :: Python :: 3.10
Classifier: Programming Language :: Python :: 3.11
Classifier: Programming Language :: Python :: 3.12
Classifier: Programming Language :: Python :: 3.13
Classifier: Programming Language :: Python :: 3.14
Classifier: Programming Language :: Python :: Implementation :: CPython
Requires-Python: >=3.10
Requires-Dist: django>=4.2
Requires-Dist: pyjwt>=2
Requires-Dist: requests>=2.30
